greasyfork_archive.py
greasyfork_archive-0.1.4.dist-info/LICENSE
greasyfork_archive-0.1.4.dist-info/METADATA
greasyfork_archive-0.1.4.dist-info/WHEEL
greasyfork_archive-0.1.4.dist-info/entry_points.txt
greasyfork_archive-0.1.4.dist-info/top_level.txt
greasyfork_archive-0.1.4.dist-info/RECORD
