Metadata-Version: 2.1
Name: greasyfork-archive
Version: 0.1.4
Summary: Scrape data from a users Greasyfork account
Home-page: https://github.com/seanbreckenridge/greasyfork_archive
Author: Sean Breckenridge
Author-email: seanbrecke@gmail.com
License: MIT
Platform: UNKNOWN
Classifier: License :: OSI Approved :: MIT License
Classifier: Programming Language :: Python
Classifier: Programming Language :: Python :: 3
Classifier: Programming Language :: Python :: 3.6
Classifier: Programming Language :: Python :: 3.7
Classifier: Programming Language :: Python :: 3.8
Classifier: Programming Language :: Python :: 3.9
License-File: LICENSE
Requires-Dist: requests (>=2.23.0)
Requires-Dist: Click (>=7.0)
Requires-Dist: beautifulsoup4 (>=4.8.2)
Requires-Dist: backoff (>=1.10.0)
